ast_matcher/__init__.py
ast_matcher/categories/__init__.py
ast_matcher/categories/base.py
ast_matcher/categories/narrowing.py
ast_matcher/categories/node.py
ast_matcher/categories/node.pyi
ast_matcher/categories/traversal.py
ast_matcher/matcher.py
ast_matcher/tree.py
ast_matcher-0.1.0.dist-info/LICENSE
ast_matcher-0.1.0.dist-info/WHEEL
ast_matcher-0.1.0.dist-info/METADATA
ast_matcher-0.1.0.dist-info/RECORD
