Metadata-Version: 2.1
Name: ast-matcher
Version: 0.1.0
Summary: 
License: MIT
Author: Sergey Reshetnikov
Author-email: resh.sersh@gmail.com
Requires-Python: >=3.9,<4.0
Classifier: License :: OSI Approved :: MIT License
Classifier: Programming Language :: Python :: 3
Requires-Dist: more-itertools (>=8.7.0,<9.0.0)
